examples/frames.py
examples/mari_cloud_minimal.py
examples/mari_edge_minimal.py
examples/mari_edge_stats.py
examples/uart.py
examples/raspberry-pi/sense_hat_ui.py
marilib/__init__.py
marilib/communication_adapter.py
marilib/logger.py
marilib/mari_protocol.py
marilib/marilib.py
marilib/marilib_cloud.py
marilib/marilib_edge.py
marilib/metrics.py
marilib/model.py
marilib/pdr.py
marilib/protocol.py
marilib/serial_hdlc.py
marilib/serial_uart.py
marilib/tui.py
marilib/tui_cloud.py
marilib/tui_edge.py
marilib/cli/cloud.py
marilib/cli/edge.py
tests/__init__.py
tests/test_hdlc.py
tests/test_protocol.py
marilib_pkg-0.8.1.dist-info/METADATA
marilib_pkg-0.8.1.dist-info/WHEEL
marilib_pkg-0.8.1.dist-info/entry_points.txt
marilib_pkg-0.8.1.dist-info/licenses/AUTHORS
marilib_pkg-0.8.1.dist-info/licenses/LICENSE
marilib_pkg-0.8.1.dist-info/RECORD
