Metadata-Version: 2.4
Name: marilib-pkg
Version: 0.8.1
Summary: MariLib is a Python library for interacting with the Mari network.
Project-URL: Homepage, https://github.com/DotBots/marilib
Project-URL: Bug Tracker, https://github.com/DotBots/marilib/issues
Author-email: Geovane Fedrecheski <geovane.fedrecheski@inria.fr>
License: BSD
License-File: AUTHORS
License-File: LICENSE
Classifier: License :: OSI Approved :: BSD License
Classifier: Operating System :: MacOS
Classifier: Operating System :: Microsoft :: Windows
Classifier: Operating System :: POSIX :: Linux
Classifier: Programming Language :: Python :: 3
Requires-Python: >=3.8
Requires-Dist: click>=8.1.7
Requires-Dist: paho-mqtt>=2.1.0
Requires-Dist: pyserial>=3.5
Requires-Dist: rich>=14.0.0
Requires-Dist: structlog>=24.4.0
Requires-Dist: tqdm>=4.66.5
